sqlalchemy_pg_fts/__init__.py
sqlalchemy_pg_fts/tsquery.py
sqlalchemy_pg_fts/tsvector.py
sqlalchemy_pg_fts/websearch.py
sqlalchemy_pg_fts-0.1.3.dist-info/WHEEL
sqlalchemy_pg_fts-0.1.3.dist-info/METADATA
sqlalchemy_pg_fts-0.1.3.dist-info/RECORD
