Metadata-Version: 2.1
Name: sqlalchemy-pg-fts
Version: 0.1.3
Summary: SqlAlchemy Postgres tsquery functionality
Home-page: https://github.com/liaden/sqlalchemy-pg-fts
License: MIT
Keywords: postgres,tsquery,sqlalchemy,full text search
Author: Joel Johnson
Author-email: johnson.joel.b@gmail.com
Requires-Python: >=3.6.13,<4.0.0
Classifier: License :: OSI Approved :: MIT License
Classifier: Programming Language :: Python :: 3
Classifier: Programming Language :: Python :: 3.10
Classifier: Programming Language :: Python :: 3.7
Classifier: Programming Language :: Python :: 3.8
Classifier: Programming Language :: Python :: 3.9
Requires-Dist: sqlalchemy (>=1.3.24,<2.0.0)
Project-URL: Repository, https://github.com/liaden/sqlalchemy-pg-fts
